rustiter/__init__.py
rustiter-0.2.0.dist-info/METADATA
rustiter-0.2.0.dist-info/WHEEL
rustiter-0.2.0.dist-info/licenses/LICENSE
rustiter-0.2.0.dist-info/RECORD
