Metadata-Version: 2.3
Name: rustiter
Version: 0.2.0
Summary: Rust iterator utilities for Python
Project-URL: Homepage, https://github.com/lxl66566/Rustiter
Project-URL: Repository, https://github.com/lxl66566/Rustiter
Author-email: lxl66566 <lxl66566@gmail.com>
License-Expression: MIT
License-File: LICENSE
Keywords: iter,iterator,rust
Classifier: License :: OSI Approved :: MIT License
Classifier: Operating System :: OS Independent
Classifier: Programming Language :: Python :: 3
Classifier: Programming Language :: Python :: 3.7
Classifier: Programming Language :: Python :: 3.8
Classifier: Programming Language :: Python :: 3.9
Classifier: Programming Language :: Python :: 3.10
Classifier: Programming Language :: Python :: 3.11
Classifier: Programming Language :: Python :: 3.12
Requires-Python: >=3.6
